growl/__init__.py
growl/base.py
growl/fista_solver.py
growl/prox_operator.py
growl_reg-0.1.2.dist-info/licenses/LICENSE
growl_reg-0.1.2.dist-info/METADATA
growl_reg-0.1.2.dist-info/WHEEL
growl_reg-0.1.2.dist-info/top_level.txt
growl_reg-0.1.2.dist-info/RECORD
