Metadata-Version: 2.4
Name: growl_reg
Version: 0.1.2
Summary: GrOWL regression estimator with OWL, OSCAR, and Lasso variants
Author: Matheus Lopes Carrijo
License-Expression: MIT
Project-URL: Homepage, https://github.com/matheuscarrijo/growl_reg
Project-URL: Repository, https://github.com/matheuscarrijo/growl_reg
Requires-Python: >=3.8
License-File: LICENSE
Requires-Dist: numpy>=1.21.0
Requires-Dist: scikit-learn>=1.0
Requires-Dist: matplotlib>=3.0.0
Dynamic: license-file
